valiqor_guardrails/__init__.py
valiqor_guardrails/checker.cp311-win_amd64.pyd
valiqor_guardrails/cli.py
valiqor_guardrails/prompts.py
valiqor_guardrails-0.1.7.dist-info/LICENSE
valiqor_guardrails-0.1.7.dist-info/METADATA
valiqor_guardrails-0.1.7.dist-info/WHEEL
valiqor_guardrails-0.1.7.dist-info/entry_points.txt
valiqor_guardrails-0.1.7.dist-info/top_level.txt
valiqor_guardrails-0.1.7.dist-info/RECORD
