Metadata-Version: 2.1
Name: valiqor-guardrails
Version: 0.1.7
Summary: LLM-driven guardrails (compiled, secure)
Author: Valiqor
Author-email: info@valiqor.com
Requires-Python: >=3.8
License-File: LICENSE
Requires-Dist: openai>=1.0.0
Requires-Dist: cython
